[
    {},
    {
        "-1": [
            {
                "damage": 15,
                "id": "minecraft:dye"
            },
            {
                "damage": 14,
                "id": "minecraft:dye"
            },
            {
                "damage": 13,
                "id": "minecraft:dye"
            },
            {
                "damage": 12,
                "id": "minecraft:dye"
            },
            {
                "damage": 11,
                "id": "minecraft:dye"
            },
            {
                "damage": 10,
                "id": "minecraft:dye"
            },
            {
                "damage": 9,
                "id": "minecraft:dye"
            },
            {
                "damage": 8,
                "id": "minecraft:dye"
            },
            {
                "damage": 7,
                "id": "minecraft:dye"
            },
            {
                "damage": 6,
                "id": "minecraft:dye"
            },
            {
                "damage": 5,
                "id": "minecraft:dye"
            },
            {
                "damage": 4,
                "id": "minecraft:dye"
            },
            {
                "damage": 3,
                "id": "minecraft:dye"
            },
            {
                "damage": 2,
                "id": "minecraft:dye"
            },
            {
                "damage": 1,
                "id": "minecraft:dye"
            },
            {
                "damage": 0,
                "id": "minecraft:dye"
            },
            "minecraft:clay_ball",
            "minecraft:clay",
            {
                "id": "minecraft:brick",
                "name": "Brick (item)"
            },
            "minecraft:hardened_clay",
            {
                "damage": 0,
                "id": "minecraft:stained_hardened_clay"
            },
            {
                "damage": 1,
                "id": "minecraft:stained_hardened_clay"
            },
            {
                "damage": 2,
                "id": "minecraft:stained_hardened_clay"
            },
            {
                "damage": 3,
                "id": "minecraft:stained_hardened_clay"
            },
            {
                "damage": 4,
                "id": "minecraft:stained_hardened_clay"
            },
            {
                "damage": 5,
                "id": "minecraft:stained_hardened_clay"
            },
            {
                "damage": 6,
                "id": "minecraft:stained_hardened_clay"
            },
            {
                "damage": 7,
                "id": "minecraft:stained_hardened_clay"
            },
            {
                "damage": 8,
                "id": "minecraft:stained_hardened_clay"
            },
            {
                "damage": 9,
                "id": "minecraft:stained_hardened_clay"
            },
            {
                "damage": 10,
                "id": "minecraft:stained_hardened_clay"
            },
            {
                "damage": 11,
                "id": "minecraft:stained_hardened_clay"
            },
            {
                "damage": 12,
                "id": "minecraft:stained_hardened_clay"
            },
            {
                "damage": 13,
                "id": "minecraft:stained_hardened_clay"
            },
            {
                "damage": 14,
                "id": "minecraft:stained_hardened_clay"
            },
            {
                "damage": 15,
                "id": "minecraft:stained_hardened_clay"
            },
            {
                "id": "minecraft:brick_block",
                "name": "Brick Block"
            },
            "minecraft:brick_stairs",
            {
                "damage": 4,
                "id": "minecraft:stone_slab"
            }
        ],
        "-2": [
            {
                "damage": 0,
                "id": "minecraft:wool"
            },
            {
                "damage": 1,
                "id": "minecraft:wool"
            },
            {
                "damage": 2,
                "id": "minecraft:wool"
            },
            {
                "damage": 3,
                "id": "minecraft:wool"
            },
            {
                "damage": 4,
                "id": "minecraft:wool"
            },
            {
                "damage": 5,
                "id": "minecraft:wool"
            },
            {
                "damage": 6,
                "id": "minecraft:wool"
            },
            {
                "damage": 7,
                "id": "minecraft:wool"
            },
            {
                "damage": 8,
                "id": "minecraft:wool"
            },
            {
                "damage": 9,
                "id": "minecraft:wool"
            },
            {
                "damage": 10,
                "id": "minecraft:wool"
            },
            {
                "damage": 11,
                "id": "minecraft:wool"
            },
            {
                "damage": 12,
                "id": "minecraft:wool"
            },
            {
                "damage": 13,
                "id": "minecraft:wool"
            },
            {
                "damage": 14,
                "id": "minecraft:wool"
            },
            {
                "damage": 15,
                "id": "minecraft:wool"
            },
            {
                "damage": 0,
                "id": "minecraft:carpet"
            },
            {
                "damage": 1,
                "id": "minecraft:carpet"
            },
            {
                "damage": 2,
                "id": "minecraft:carpet"
            },
            {
                "damage": 3,
                "id": "minecraft:carpet"
            },
            {
                "damage": 4,
                "id": "minecraft:carpet"
            },
            {
                "damage": 5,
                "id": "minecraft:carpet"
            },
            {
                "damage": 6,
                "id": "minecraft:carpet"
            },
            {
                "damage": 7,
                "id": "minecraft:carpet"
            },
            {
                "damage": 8,
                "id": "minecraft:carpet"
            },
            {
                "damage": 9,
                "id": "minecraft:carpet"
            },
            {
                "damage": 10,
                "id": "minecraft:carpet"
            },
            {
                "damage": 11,
                "id": "minecraft:carpet"
            },
            {
                "damage": 12,
                "id": "minecraft:carpet"
            },
            {
                "damage": 13,
                "id": "minecraft:carpet"
            },
            {
                "damage": 14,
                "id": "minecraft:carpet"
            },
            {
                "damage": 15,
                "id": "minecraft:carpet"
            },
            {
                "damage": 15,
                "id": "minecraft:banner"
            },
            {
                "damage": 14,
                "id": "minecraft:banner"
            },
            {
                "damage": 13,
                "id": "minecraft:banner"
            },
            {
                "damage": 12,
                "id": "minecraft:banner"
            },
            {
                "damage": 11,
                "id": "minecraft:banner"
            },
            {
                "damage": 10,
                "id": "minecraft:banner"
            },
            {
                "damage": 9,
                "id": "minecraft:banner"
            },
            {
                "damage": 8,
                "id": "minecraft:banner"
            },
            {
                "damage": 7,
                "id": "minecraft:banner"
            },
            {
                "damage": 6,
                "id": "minecraft:banner"
            },
            {
                "damage": 5,
                "id": "minecraft:banner"
            },
            {
                "damage": 4,
                "id": "minecraft:banner"
            },
            {
                "damage": 3,
                "id": "minecraft:banner"
            },
            {
                "damage": 2,
                "id": "minecraft:banner"
            },
            {
                "damage": 1,
                "id": "minecraft:banner"
            },
            {
                "damage": 0,
                "id": "minecraft:banner"
            }
        ],
        "-3": [
            "minecraft:glass",
            "minecraft:glass_pane",
            {
                "damage": 0,
                "id": "minecraft:stained_glass"
            },
            {
                "damage": 0,
                "id": "minecraft:stained_glass_pane"
            },
            {
                "damage": 1,
                "id": "minecraft:stained_glass"
            },
            {
                "damage": 1,
                "id": "minecraft:stained_glass_pane"
            },
            {
                "damage": 2,
                "id": "minecraft:stained_glass"
            },
            {
                "damage": 2,
                "id": "minecraft:stained_glass_pane"
            },
            {
                "damage": 3,
                "id": "minecraft:stained_glass"
            },
            {
                "damage": 3,
                "id": "minecraft:stained_glass_pane"
            },
            {
                "damage": 4,
                "id": "minecraft:stained_glass"
            },
            {
                "damage": 4,
                "id": "minecraft:stained_glass_pane"
            },
            {
                "damage": 5,
                "id": "minecraft:stained_glass"
            },
            {
                "damage": 5,
                "id": "minecraft:stained_glass_pane"
            },
            {
                "damage": 6,
                "id": "minecraft:stained_glass"
            },
            {
                "damage": 6,
                "id": "minecraft:stained_glass_pane"
            },
            {
                "damage": 7,
                "id": "minecraft:stained_glass"
            },
            {
                "damage": 7,
                "id": "minecraft:stained_glass_pane"
            },
            {
                "damage": 8,
                "id": "minecraft:stained_glass"
            },
            {
                "damage": 8,
                "id": "minecraft:stained_glass_pane"
            },
            {
                "damage": 9,
                "id": "minecraft:stained_glass"
            },
            {
                "damage": 9,
                "id": "minecraft:stained_glass_pane"
            },
            {
                "damage": 10,
                "id": "minecraft:stained_glass"
            },
            {
                "damage": 10,
                "id": "minecraft:stained_glass_pane"
            },
            {
                "damage": 11,
                "id": "minecraft:stained_glass"
            },
            {
                "damage": 11,
                "id": "minecraft:stained_glass_pane"
            },
            {
                "damage": 12,
                "id": "minecraft:stained_glass"
            },
            {
                "damage": 12,
                "id": "minecraft:stained_glass_pane"
            },
            {
                "damage": 13,
                "id": "minecraft:stained_glass"
            },
            {
                "damage": 13,
                "id": "minecraft:stained_glass_pane"
            },
            {
                "damage": 14,
                "id": "minecraft:stained_glass"
            },
            {
                "damage": 14,
                "id": "minecraft:stained_glass_pane"
            },
            {
                "damage": 15,
                "id": "minecraft:stained_glass"
            },
            {
                "damage": 15,
                "id": "minecraft:stained_glass_pane"
            }
        ],
        "0": [
            {
                "damage": 0,
                "id": "minecraft:stone"
            },
            {
                "damage": 0,
                "id": "minecraft:dirt"
            },
            "minecraft:cobblestone",
            {
                "damage": 0,
                "id": "minecraft:stonebrick"
            },
            {
                "damage": 0,
                "id": "minecraft:quartz_block",
                "name": "Quartz Block"
            },
            "minecraft:iron_bars",
            {
                "damage": 0,
                "id": "minecraft:sandstone"
            },
            {
                "damage": 0,
                "id": "minecraft:red_sandstone"
            },
            {
                "damage": 0,
                "id": "minecraft:sand"
            },
            {
                "damage": 1,
                "id": "minecraft:sand"
            },
            "minecraft:gravel",
            "minecraft:grass",
            "minecraft:mycelium",
            {
                "damage": 2,
                "id": "minecraft:dirt"
            },
            {
                "damage": 1,
                "id": "minecraft:dirt"
            },
            "minecraft:obsidian",
            "minecraft:ice",
            "minecraft:packed_ice",
            "minecraft:snow",
            {
                "id": "minecraft:snow_layer",
                "name": "Snow Layer"
            },
            {
                "damage": 1,
                "id": "minecraft:stone"
            },
            {
                "damage": 2,
                "id": "minecraft:stone"
            },
            {
                "damage": 3,
                "id": "minecraft:stone"
            },
            {
                "damage": 4,
                "id": "minecraft:stone"
            },
            {
                "damage": 5,
                "id": "minecraft:stone"
            },
            {
                "damage": 6,
                "id": "minecraft:stone"
            },
            "minecraft:sandstone_stairs",
            "minecraft:red_sandstone_stairs",
            {
                "damage": 1,
                "id": "minecraft:stone_slab"
            },
            {
                "damage": 0,
                "id": "minecraft:stone_slab2"
            },
            {
                "damage": 2,
                "id": "minecraft:sandstone"
            },
            {
                "damage": 2,
                "id": "minecraft:red_sandstone"
            },
            {
                "damage": 1,
                "id": "minecraft:sandstone"
            },
            {
                "damage": 1,
                "id": "minecraft:red_sandstone"
            },
            {
                "damage": 0,
                "id": "minecraft:stone_slab"
            },
            "minecraft:stone_stairs",
            {
                "damage": 3,
                "id": "minecraft:stone_slab"
            },
            {
                "damage": 0,
                "id": "minecraft:cobblestone_wall"
            },
            "minecraft:mossy_cobblestone",
            {
                "damage": 1,
                "id": "minecraft:cobblestone_wall"
            },
            "minecraft:stone_brick_stairs",
            {
                "damage": 5,
                "id": "minecraft:stone_slab"
            },
            {
                "damage": 1,
                "id": "minecraft:stonebrick"
            },
            {
                "damage": 2,
                "id": "minecraft:stonebrick"
            },
            {
                "damage": 3,
                "id": "minecraft:stonebrick"
            },
            "minecraft:quartz_stairs",
            {
                "damage": 7,
                "id": "minecraft:stone_slab"
            },
            {
                "damage": 2,
                "id": "minecraft:quartz_block"
            },
            {
                "damage": 1,
                "id": "minecraft:quartz_block"
            }
        ],
        "1": [
            "minecraft:ender_pearl",
            "minecraft:crafting_table",
            "minecraft:furnace",
            "minecraft:torch",
            "minecraft:chest",
            "minecraft:trapped_chest",
            "minecraft:ender_chest",
            "minecraft:enchanting_table",
            {
                "damage": 0,
                "id": "minecraft:anvil",
                "name": "Anvil (undamaged)"
            },
            {
                "damage": 1,
                "id": "minecraft:anvil"
            },
            {
                "damage": 2,
                "id": "minecraft:anvil"
            },
            "minecraft:sign",
            "minecraft:item_frame",
            "minecraft:bucket",
            "minecraft:water_bucket",
            "minecraft:lava_bucket",
            "minecraft:flint",
            "minecraft:bed",
            "minecraft:map",
            "minecraft:ender_eye",
            "minecraft:ladder",
            "minecraft:name_tag",
            "minecraft:saddle",
            "minecraft:lead",
            "minecraft:armor_stand",
            "minecraft:painting",
            "minecraft:flower_pot",
            "minecraft:beacon",
            "minecraft:end_crystal"
        ]
    },
    {
        "-1": [
            "minecraft:cake",
            "minecraft:rabbit_stew",
            "minecraft:cooked_porkchop",
            "minecraft:cooked_beef",
            "minecraft:pumpkin_pie",
            "minecraft:golden_carrot",
            "minecraft:cooked_mutton",
            {
                "damage": 1,
                "id": "minecraft:cooked_fish"
            },
            "minecraft:cooked_chicken",
            "minecraft:mushroom_stew",
            "minecraft:baked_potato",
            "minecraft:beetroot_soup",
            "minecraft:bread",
            {
                "damage": 0,
                "id": "minecraft:cooked_fish"
            },
            "minecraft:cooked_rabbit",
            {
                "damage": 0,
                "id": "minecraft:golden_apple"
            },
            {
                "damage": 1,
                "id": "minecraft:golden_apple"
            },
            "minecraft:apple",
            "minecraft:chorus_fruit",
            "minecraft:rotten_flesh",
            "minecraft:carrot",
            "minecraft:beef",
            "minecraft:porkchop",
            "minecraft:spider_eye",
            "minecraft:rabbit",
            {
                "id": "minecraft:melon",
                "name": "Melon Slice"
            },
            "minecraft:poisonous_potato",
            "minecraft:chicken",
            "minecraft:mutton",
            "minecraft:cookie",
            {
                "damage": 0,
                "id": "minecraft:fish"
            },
            {
                "damage": 1,
                "id": "minecraft:fish"
            },
            "minecraft:beetroot",
            "minecraft:potato",
            {
                "damage": 2,
                "id": "minecraft:fish"
            },
            {
                "damage": 3,
                "id": "minecraft:fish"
            }
        ],
        "-2": [
            "minecraft:milk_bucket",
            "minecraft:bowl",
            "minecraft:string",
            "minecraft:bone",
            "minecraft:rabbit_foot",
            "minecraft:rabbit_hide",
            "minecraft:leather",
            "minecraft:feather",
            "minecraft:slime_ball",
            "minecraft:egg",
            "minecraft:gunpowder",
            "minecraft:nether_star",
            {
                "damage": 0,
                "id": "minecraft:skull"
            },
            {
                "damage": 1,
                "id": "minecraft:skull"
            },
            {
                "damage": 2,
                "id": "minecraft:skull"
            },
            {
                "damage": 4,
                "id": "minecraft:skull"
            },
            {
                "damage": 5,
                "id": "minecraft:skull"
            },
            "minecraft:slime",
            "minecraft:web",
            "minecraft:bone_block",
            "minecraft:totem_of_undying"
        ],
        "0": [
            "minecraft:redstone",
            {
                "id": "minecraft:redstone_block",
                "name": "Redstone Block"
            },
            "minecraft:redstone_torch",
            "minecraft:redstone_lamp",
            "minecraft:repeater",
            "minecraft:comparator",
            "minecraft:piston",
            "minecraft:sticky_piston",
            "minecraft:daylight_detector",
            "minecraft:lever",
            "minecraft:wooden_button",
            "minecraft:stone_button",
            "minecraft:tripwire_hook",
            "minecraft:hopper",
            "minecraft:dispenser",
            "minecraft:dropper",
            "minecraft:tnt",
            "minecraft:rail",
            "minecraft:golden_rail",
            "minecraft:detector_rail",
            "minecraft:activator_rail",
            "minecraft:minecart",
            "minecraft:chest_minecart",
            "minecraft:furnace_minecart",
            "minecraft:hopper_minecart",
            "minecraft:tnt_minecart",
            "minecraft:wooden_pressure_plate",
            "minecraft:stone_pressure_plate",
            {
                "id": "minecraft:light_weighted_pressure_plate",
                "name": "Gold Pressure Plate (weighted pressure plate, light)"
            },
            {
                "id": "minecraft:heavy_weighted_pressure_plate",
                "name": "Iron Pressure Plate (weighted pressure plate, heavy)"
            },
            "minecraft:iron_door",
            "minecraft:iron_trapdoor",
            "minecraft:noteblock",
            "minecraft:observer"
        ],
        "1": [
            "minecraft:stick",
            "minecraft:trapdoor",
            {
                "damage": 0,
                "id": "minecraft:sapling"
            },
            {
                "damage": 1,
                "id": "minecraft:sapling"
            },
            {
                "damage": 2,
                "id": "minecraft:sapling"
            },
            {
                "damage": 3,
                "id": "minecraft:sapling"
            },
            {
                "damage": 4,
                "id": "minecraft:sapling"
            },
            {
                "damage": 5,
                "id": "minecraft:sapling"
            },
            {
                "damage": 0,
                "id": "minecraft:log"
            },
            {
                "damage": 1,
                "id": "minecraft:log"
            },
            {
                "damage": 2,
                "id": "minecraft:log"
            },
            {
                "damage": 3,
                "id": "minecraft:log"
            },
            {
                "damage": 0,
                "id": "minecraft:log2"
            },
            {
                "damage": 1,
                "id": "minecraft:log2"
            },
            {
                "damage": 0,
                "id": "minecraft:planks"
            },
            {
                "damage": 1,
                "id": "minecraft:planks"
            },
            {
                "damage": 2,
                "id": "minecraft:planks"
            },
            {
                "damage": 3,
                "id": "minecraft:planks"
            },
            {
                "damage": 4,
                "id": "minecraft:planks"
            },
            {
                "damage": 5,
                "id": "minecraft:planks"
            },
            "minecraft:oak_stairs",
            "minecraft:spruce_stairs",
            "minecraft:birch_stairs",
            "minecraft:jungle_stairs",
            "minecraft:acacia_stairs",
            "minecraft:dark_oak_stairs",
            {
                "damage": 0,
                "id": "minecraft:wooden_slab"
            },
            {
                "damage": 1,
                "id": "minecraft:wooden_slab"
            },
            {
                "damage": 2,
                "id": "minecraft:wooden_slab"
            },
            {
                "damage": 3,
                "id": "minecraft:wooden_slab"
            },
            {
                "damage": 4,
                "id": "minecraft:wooden_slab"
            },
            {
                "damage": 5,
                "id": "minecraft:wooden_slab"
            },
            {
                "damage": 2,
                "id": "minecraft:stone_slab"
            }
        ],
        "2": [
            "minecraft:fence",
            "minecraft:fence_gate",
            "minecraft:spruce_fence",
            "minecraft:spruce_fence_gate",
            "minecraft:birch_fence",
            "minecraft:birch_fence_gate",
            "minecraft:jungle_fence",
            "minecraft:jungle_fence_gate",
            "minecraft:acacia_fence",
            "minecraft:acacia_fence_gate",
            "minecraft:dark_oak_fence",
            "minecraft:dark_oak_fence_gate",
            "minecraft:wooden_door",
            "minecraft:spruce_door",
            "minecraft:birch_door",
            "minecraft:jungle_door",
            "minecraft:acacia_door",
            "minecraft:dark_oak_door",
            {
                "damage": 0,
                "id": "minecraft:leaves"
            },
            {
                "damage": 1,
                "id": "minecraft:leaves"
            },
            {
                "damage": 2,
                "id": "minecraft:leaves"
            },
            {
                "damage": 3,
                "id": "minecraft:leaves"
            },
            {
                "damage": 0,
                "id": "minecraft:leaves2"
            },
            {
                "damage": 1,
                "id": "minecraft:leaves2"
            },
            "minecraft:boat",
            "minecraft:spruce_boat",
            "minecraft:birch_boat",
            "minecraft:jungle_boat",
            "minecraft:acacia_boat",
            "minecraft:dark_oak_boat"
        ]
    },
    {
        "-1": [
            {
                "damage": 0,
                "id": "minecraft:sponge"
            },
            {
                "damage": 1,
                "id": "minecraft:sponge"
            },
            "minecraft:sea_lantern",
            {
                "damage": 0,
                "id": "minecraft:prismarine"
            },
            {
                "damage": 1,
                "id": "minecraft:prismarine"
            },
            {
                "damage": 2,
                "id": "minecraft:prismarine"
            },
            "minecraft:prismarine_shard",
            "minecraft:prismarine_crystals"
        ],
        "0": [
            {
                "damage": 0,
                "id": "minecraft:coal"
            },
            {
                "damage": 1,
                "id": "minecraft:coal"
            },
            "minecraft:iron_nugget",
            "minecraft:iron_ingot",
            "minecraft:gold_nugget",
            "minecraft:gold_ingot",
            "minecraft:diamond",
            "minecraft:emerald",
            {
                "id": "minecraft:coal_block",
                "name": "Coal Block"
            },
            {
                "id": "minecraft:iron_block",
                "name": "Iron Block"
            },
            {
                "id": "minecraft:gold_block",
                "name": "Gold Block"
            },
            "minecraft:lapis_block",
            {
                "id": "minecraft:diamond_block",
                "name": "Diamond Block"
            },
            {
                "id": "minecraft:emerald_block",
                "name": "Emerald Block"
            },
            "minecraft:coal_ore",
            "minecraft:iron_ore",
            "minecraft:gold_ore",
            "minecraft:lapis_ore",
            "minecraft:redstone_ore",
            "minecraft:diamond_ore",
            "minecraft:emerald_ore",
            "minecraft:quartz_ore"
        ],
        "1": [
            "minecraft:netherrack",
            "minecraft:soul_sand",
            "minecraft:glowstone_dust",
            {
                "id": "minecraft:glowstone",
                "name": "Glowstone Block"
            },
            {
                "id": "minecraft:netherbrick",
                "name": "Nether Brick (item)"
            },
            {
                "id": "minecraft:nether_brick",
                "name": "Nether Brick Block"
            },
            "minecraft:magma",
            "minecraft:nether_wart_block",
            "minecraft:red_nether_brick",
            {
                "damage": 6,
                "id": "minecraft:stone_slab"
            },
            "minecraft:nether_brick_stairs",
            "minecraft:nether_brick_fence",
            "minecraft:quartz"
        ]
    },
    {
        "-1": [
            "minecraft:brewing_stand",
            "minecraft:cauldron",
            "minecraft:glass_bottle",
            "minecraft:dragon_breath",
            "minecraft:nether_wart",
            "minecraft:fermented_spider_eye",
            "minecraft:blaze_rod",
            "minecraft:blaze_powder",
            "minecraft:sugar",
            "minecraft:ghast_tear",
            "minecraft:speckled_melon",
            "minecraft:magma_cream",
            {
                "effect": "minecraft:water",
                "id": "minecraft:potion"
            },
            {
                "effect": "minecraft:water",
                "id": "minecraft:splash_potion"
            },
            {
                "effect": "minecraft:water",
                "id": "minecraft:lingering_potion"
            },
            {
                "effect": "minecraft:awkward",
                "id": "minecraft:lingering_potion"
            },
            {
                "effect": "minecraft:awkward",
                "id": "minecraft:potion"
            },
            {
                "effect": "minecraft:awkward",
                "id": "minecraft:splash_potion"
            },
            {
                "effect": "minecraft:mundane",
                "id": "minecraft:potion"
            },
            {
                "effect": "minecraft:mundane",
                "id": "minecraft:splash_potion"
            },
            {
                "effect": "minecraft:mundane",
                "id": "minecraft:lingering_potion"
            },
            {
                "effect": "minecraft:thick",
                "id": "minecraft:lingering_potion"
            },
            {
                "effect": "minecraft:thick",
                "id": "minecraft:potion"
            },
            {
                "effect": "minecraft:thick",
                "id": "minecraft:splash_potion"
            },
            "minecraft:experience_bottle"
        ],
        "-2": [
            {
                "effect": "minecraft:swiftness",
                "id": "minecraft:potion"
            },
            {
                "effect": "minecraft:swiftness",
                "id": "minecraft:splash_potion"
            },
            {
                "effect": "minecraft:swiftness",
                "id": "minecraft:lingering_potion"
            },
            {
                "effect": "minecraft:swiftness",
                "id": "minecraft:tipped_arrow"
            },
            {
                "effect": "minecraft:long_swiftness",
                "id": "minecraft:potion"
            },
            {
                "effect": "minecraft:long_swiftness",
                "id": "minecraft:splash_potion"
            },
            {
                "effect": "minecraft:long_swiftness",
                "id": "minecraft:lingering_potion"
            },
            {
                "effect": "minecraft:long_swiftness",
                "id": "minecraft:tipped_arrow"
            },
            {
                "effect": "minecraft:strong_swiftness",
                "id": "minecraft:potion"
            },
            {
                "effect": "minecraft:strong_swiftness",
                "id": "minecraft:splash_potion"
            },
            {
                "effect": "minecraft:strong_swiftness",
                "id": "minecraft:lingering_potion"
            },
            {
                "effect": "minecraft:strong_swiftness",
                "id": "minecraft:tipped_arrow"
            },
            {
                "effect": "minecraft:strength",
                "id": "minecraft:potion"
            },
            {
                "effect": "minecraft:strength",
                "id": "minecraft:splash_potion"
            },
            {
                "effect": "minecraft:strength",
                "id": "minecraft:lingering_potion"
            },
            {
                "effect": "minecraft:strength",
                "id": "minecraft:tipped_arrow"
            },
            {
                "effect": "minecraft:long_strength",
                "id": "minecraft:potion"
            },
            {
                "effect": "minecraft:long_strength",
                "id": "minecraft:splash_potion"
            },
            {
                "effect": "minecraft:long_strength",
                "id": "minecraft:lingering_potion"
            },
            {
                "effect": "minecraft:long_strength",
                "id": "minecraft:tipped_arrow"
            },
            {
                "effect": "minecraft:strong_strength",
                "id": "minecraft:potion"
            },
            {
                "effect": "minecraft:strong_strength",
                "id": "minecraft:splash_potion"
            },
            {
                "effect": "minecraft:strong_strength",
                "id": "minecraft:lingering_potion"
            },
            {
                "effect": "minecraft:strong_strength",
                "id": "minecraft:tipped_arrow"
            },
            {
                "effect": "minecraft:healing",
                "id": "minecraft:potion"
            },
            {
                "effect": "minecraft:healing",
                "id": "minecraft:splash_potion"
            },
            {
                "effect": "minecraft:healing",
                "id": "minecraft:lingering_potion"
            },
            {
                "effect": "minecraft:healing",
                "id": "minecraft:tipped_arrow"
            },
            {
                "effect": "minecraft:strong_healing",
                "id": "minecraft:potion"
            },
            {
                "effect": "minecraft:strong_healing",
                "id": "minecraft:splash_potion"
            },
            {
                "effect": "minecraft:strong_healing",
                "id": "minecraft:lingering_potion"
            },
            {
                "effect": "minecraft:strong_healing",
                "id": "minecraft:tipped_arrow"
            },
            {
                "effect": "minecraft:leaping",
                "id": "minecraft:potion"
            },
            {
                "effect": "minecraft:leaping",
                "id": "minecraft:splash_potion"
            },
            {
                "effect": "minecraft:leaping",
                "id": "minecraft:lingering_potion"
            },
            {
                "effect": "minecraft:leaping",
                "id": "minecraft:tipped_arrow"
            },
            {
                "effect": "minecraft:long_leaping",
                "id": "minecraft:potion"
            },
            {
                "effect": "minecraft:long_leaping",
                "id": "minecraft:splash_potion"
            },
            {
                "effect": "minecraft:long_leaping",
                "id": "minecraft:lingering_potion"
            },
            {
                "effect": "minecraft:long_leaping",
                "id": "minecraft:tipped_arrow"
            },
            {
                "effect": "minecraft:strong_leaping",
                "id": "minecraft:potion"
            },
            {
                "effect": "minecraft:strong_leaping",
                "id": "minecraft:splash_potion"
            },
            {
                "effect": "minecraft:strong_leaping",
                "id": "minecraft:lingering_potion"
            },
            {
                "effect": "minecraft:strong_leaping",
                "id": "minecraft:tipped_arrow"
            },
            {
                "effect": "minecraft:regeneration",
                "id": "minecraft:potion"
            },
            {
                "effect": "minecraft:regeneration",
                "id": "minecraft:splash_potion"
            },
            {
                "effect": "minecraft:regeneration",
                "id": "minecraft:lingering_potion"
            },
            {
                "effect": "minecraft:regeneration",
                "id": "minecraft:tipped_arrow"
            },
            {
                "effect": "minecraft:long_regeneration",
                "id": "minecraft:potion"
            },
            {
                "effect": "minecraft:long_regeneration",
                "id": "minecraft:splash_potion"
            },
            {
                "effect": "minecraft:long_regeneration",
                "id": "minecraft:lingering_potion"
            },
            {
                "effect": "minecraft:long_regeneration",
                "id": "minecraft:tipped_arrow"
            },
            {
                "effect": "minecraft:strong_regeneration",
                "id": "minecraft:potion"
            },
            {
                "effect": "minecraft:strong_regeneration",
                "id": "minecraft:splash_potion"
            },
            {
                "effect": "minecraft:strong_regeneration",
                "id": "minecraft:lingering_potion"
            },
            {
                "effect": "minecraft:strong_regeneration",
                "id": "minecraft:tipped_arrow"
            },
            {
                "effect": "minecraft:fire_resistance",
                "id": "minecraft:potion"
            },
            {
                "effect": "minecraft:fire_resistance",
                "id": "minecraft:splash_potion"
            },
            {
                "effect": "minecraft:fire_resistance",
                "id": "minecraft:lingering_potion"
            },
            {
                "effect": "minecraft:fire_resistance",
                "id": "minecraft:tipped_arrow"
            },
            {
                "effect": "minecraft:long_fire_resistance",
                "id": "minecraft:potion"
            },
            {
                "effect": "minecraft:long_fire_resistance",
                "id": "minecraft:splash_potion"
            },
            {
                "effect": "minecraft:long_fire_resistance",
                "id": "minecraft:lingering_potion"
            },
            {
                "effect": "minecraft:long_fire_resistance",
                "id": "minecraft:tipped_arrow"
            },
            {
                "effect": "minecraft:water_breathing",
                "id": "minecraft:potion"
            },
            {
                "effect": "minecraft:water_breathing",
                "id": "minecraft:splash_potion"
            },
            {
                "effect": "minecraft:water_breathing",
                "id": "minecraft:lingering_potion"
            },
            {
                "effect": "minecraft:water_breathing",
                "id": "minecraft:tipped_arrow"
            },
            {
                "effect": "minecraft:long_water_breathing",
                "id": "minecraft:potion"
            },
            {
                "effect": "minecraft:long_water_breathing",
                "id": "minecraft:splash_potion"
            },
            {
                "effect": "minecraft:long_water_breathing",
                "id": "minecraft:lingering_potion"
            },
            {
                "effect": "minecraft:long_water_breathing",
                "id": "minecraft:tipped_arrow"
            },
            {
                "effect": "minecraft:invisibility",
                "id": "minecraft:potion"
            },
            {
                "effect": "minecraft:invisibility",
                "id": "minecraft:splash_potion"
            },
            {
                "effect": "minecraft:invisibility",
                "id": "minecraft:lingering_potion"
            },
            {
                "effect": "minecraft:invisibility",
                "id": "minecraft:tipped_arrow"
            },
            {
                "effect": "minecraft:long_invisibility",
                "id": "minecraft:potion"
            },
            {
                "effect": "minecraft:long_invisibility",
                "id": "minecraft:splash_potion"
            },
            {
                "effect": "minecraft:long_invisibility",
                "id": "minecraft:lingering_potion"
            },
            {
                "effect": "minecraft:long_invisibility",
                "id": "minecraft:tipped_arrow"
            },
            {
                "effect": "minecraft:night_vision",
                "id": "minecraft:potion"
            },
            {
                "effect": "minecraft:night_vision",
                "id": "minecraft:splash_potion"
            },
            {
                "effect": "minecraft:night_vision",
                "id": "minecraft:lingering_potion"
            },
            {
                "effect": "minecraft:night_vision",
                "id": "minecraft:tipped_arrow"
            },
            {
                "effect": "minecraft:long_night_vision",
                "id": "minecraft:potion"
            },
            {
                "effect": "minecraft:long_night_vision",
                "id": "minecraft:splash_potion"
            },
            {
                "effect": "minecraft:long_night_vision",
                "id": "minecraft:lingering_potion"
            },
            {
                "effect": "minecraft:long_night_vision",
                "id": "minecraft:tipped_arrow"
            }
        ],
        "-3": [
            {
                "effect": "minecraft:slowness",
                "id": "minecraft:potion"
            },
            {
                "effect": "minecraft:slowness",
                "id": "minecraft:splash_potion"
            },
            {
                "effect": "minecraft:slowness",
                "id": "minecraft:lingering_potion"
            },
            {
                "effect": "minecraft:slowness",
                "id": "minecraft:tipped_arrow"
            },
            {
                "effect": "minecraft:long_slowness",
                "id": "minecraft:potion"
            },
            {
                "effect": "minecraft:long_slowness",
                "id": "minecraft:splash_potion"
            },
            {
                "effect": "minecraft:long_slowness",
                "id": "minecraft:lingering_potion"
            },
            {
                "effect": "minecraft:long_slowness",
                "id": "minecraft:tipped_arrow"
            },
            {
                "effect": "minecraft:harming",
                "id": "minecraft:potion"
            },
            {
                "effect": "minecraft:harming",
                "id": "minecraft:splash_potion"
            },
            {
                "effect": "minecraft:harming",
                "id": "minecraft:lingering_potion"
            },
            {
                "effect": "minecraft:harming",
                "id": "minecraft:tipped_arrow"
            },
            {
                "effect": "minecraft:strong_harming",
                "id": "minecraft:potion"
            },
            {
                "effect": "minecraft:strong_harming",
                "id": "minecraft:splash_potion"
            },
            {
                "effect": "minecraft:strong_harming",
                "id": "minecraft:lingering_potion"
            },
            {
                "effect": "minecraft:strong_harming",
                "id": "minecraft:tipped_arrow"
            },
            {
                "effect": "minecraft:weakness",
                "id": "minecraft:potion"
            },
            {
                "effect": "minecraft:weakness",
                "id": "minecraft:splash_potion"
            },
            {
                "effect": "minecraft:weakness",
                "id": "minecraft:lingering_potion"
            },
            {
                "effect": "minecraft:weakness",
                "id": "minecraft:tipped_arrow"
            },
            {
                "effect": "minecraft:long_weakness",
                "id": "minecraft:potion"
            },
            {
                "effect": "minecraft:long_weakness",
                "id": "minecraft:splash_potion"
            },
            {
                "effect": "minecraft:long_weakness",
                "id": "minecraft:lingering_potion"
            },
            {
                "effect": "minecraft:long_weakness",
                "id": "minecraft:tipped_arrow"
            },
            {
                "effect": "minecraft:poison",
                "id": "minecraft:potion"
            },
            {
                "effect": "minecraft:poison",
                "id": "minecraft:splash_potion"
            },
            {
                "effect": "minecraft:poison",
                "id": "minecraft:lingering_potion"
            },
            {
                "effect": "minecraft:poison",
                "id": "minecraft:tipped_arrow"
            },
            {
                "effect": "minecraft:long_poison",
                "id": "minecraft:potion"
            },
            {
                "effect": "minecraft:long_poison",
                "id": "minecraft:splash_potion"
            },
            {
                "effect": "minecraft:long_poison",
                "id": "minecraft:lingering_potion"
            },
            {
                "effect": "minecraft:long_poison",
                "id": "minecraft:tipped_arrow"
            },
            {
                "effect": "minecraft:strong_poison",
                "id": "minecraft:potion"
            },
            {
                "effect": "minecraft:strong_poison",
                "id": "minecraft:splash_potion"
            },
            {
                "effect": "minecraft:strong_poison",
                "id": "minecraft:lingering_potion"
            },
            {
                "effect": "minecraft:strong_poison",
                "id": "minecraft:tipped_arrow"
            }
        ],
        "0": [
            "minecraft:wheat_seeds",
            "minecraft:wheat",
            "minecraft:melon_seeds",
            {
                "id": "minecraft:melon_block",
                "name": "Melon Block"
            },
            "minecraft:pumpkin_seeds",
            "minecraft:pumpkin",
            "minecraft:beetroot_seeds",
            "minecraft:lit_pumpkin",
            "minecraft:reeds",
            "minecraft:cactus",
            "minecraft:brown_mushroom",
            "minecraft:red_mushroom",
            "minecraft:brown_mushroom_block",
            "minecraft:red_mushroom_block",
            "minecraft:yellow_flower",
            {
                "damage": 0,
                "id": "minecraft:red_flower"
            },
            {
                "damage": 1,
                "id": "minecraft:red_flower"
            },
            {
                "damage": 2,
                "id": "minecraft:red_flower"
            },
            {
                "damage": 3,
                "id": "minecraft:red_flower"
            },
            {
                "damage": 4,
                "id": "minecraft:red_flower"
            },
            {
                "damage": 5,
                "id": "minecraft:red_flower"
            },
            {
                "damage": 6,
                "id": "minecraft:red_flower"
            },
            {
                "damage": 7,
                "id": "minecraft:red_flower"
            },
            {
                "damage": 8,
                "id": "minecraft:red_flower"
            },
            {
                "damage": 0,
                "id": "minecraft:double_plant"
            },
            {
                "damage": 1,
                "id": "minecraft:double_plant"
            },
            {
                "damage": 4,
                "id": "minecraft:double_plant"
            },
            {
                "damage": 5,
                "id": "minecraft:double_plant"
            },
            {
                "damage": 1,
                "id": "minecraft:tallgrass"
            },
            {
                "damage": 2,
                "id": "minecraft:tallgrass"
            },
            "minecraft:deadbush",
            "minecraft:vine",
            "minecraft:waterlily",
            "minecraft:hay_block",
            "minecraft:diamond_hoe",
            "minecraft:iron_hoe",
            "minecraft:stone_hoe",
            "minecraft:wooden_hoe",
            "minecraft:golden_hoe"
        ],
        "1": [
            "minecraft:end_stone",
            "minecraft:end_bricks",
            "minecraft:end_rod",
            "minecraft:dragon_egg",
            "minecraft:chorus_flower",
            "minecraft:chorus_fruit_popped",
            "minecraft:purpur_block",
            "minecraft:purpur_pillar",
            "minecraft:purpur_slab",
            "minecraft:purpur_stairs",
            "minecraft:shulker_shell"
        ]
    },
    {
        "-1": [
            "minecraft:diamond_helmet",
            "minecraft:diamond_chestplate",
            "minecraft:diamond_leggings",
            "minecraft:diamond_boots",
            "minecraft:iron_helmet",
            "minecraft:iron_chestplate",
            "minecraft:iron_leggings",
            "minecraft:iron_boots",
            "minecraft:chainmail_helmet",
            "minecraft:chainmail_chestplate",
            "minecraft:chainmail_leggings",
            "minecraft:chainmail_boots",
            "minecraft:golden_helmet",
            "minecraft:golden_chestplate",
            "minecraft:golden_leggings",
            "minecraft:golden_boots",
            "minecraft:leather_helmet",
            "minecraft:leather_chestplate",
            "minecraft:leather_leggings",
            "minecraft:leather_boots",
            "minecraft:diamond_horse_armor",
            "minecraft:golden_horse_armor",
            "minecraft:iron_horse_armor",
            "minecraft:elytra"
        ],
        "0": [
            {
                "id": "minecraft:compass",
                "sorter": 10
            },
            {
                "id": "minecraft:clock",
                "sorter": 15
            },
            "minecraft:shears",
            "minecraft:fishing_rod",
            "minecraft:diamond_pickaxe",
            "minecraft:diamond_shovel",
            "minecraft:diamond_axe",
            "minecraft:iron_pickaxe",
            "minecraft:iron_shovel",
            "minecraft:iron_axe",
            "minecraft:flint_and_steel",
            "minecraft:stone_pickaxe",
            "minecraft:stone_shovel",
            "minecraft:stone_axe",
            "minecraft:wooden_pickaxe",
            "minecraft:wooden_shovel",
            "minecraft:wooden_axe",
            "minecraft:golden_pickaxe",
            "minecraft:golden_shovel",
            "minecraft:golden_axe",
            "minecraft:carrot_on_a_stick"
        ],
        "1": [
            "minecraft:bow",
            {
                "id": "minecraft:arrow",
                "sorter": 11
            },
            "minecraft:diamond_sword",
            "minecraft:iron_sword",
            "minecraft:stone_sword",
            "minecraft:wooden_sword",
            "minecraft:golden_sword",
            {
                "id": "minecraft:fire_charge",
                "sorter": 12
            },
            {
                "id": "minecraft:snowball",
                "sorter": 13
            },
            {
                "id": "minecraft:shield",
                "tagValue": null
            },
            {
                "id": "minecraft:spectral_arrow",
                "sorter": 14
            }
        ]
    },
    {
        "-1": [
            "minecraft:white_shulker_box",
            "minecraft:orange_shulker_box",
            "minecraft:magenta_shulker_box",
            "minecraft:light_blue_shulker_box",
            "minecraft:yellow_shulker_box",
            "minecraft:lime_shulker_box",
            "minecraft:pink_shulker_box",
            "minecraft:gray_shulker_box",
            "minecraft:silver_shulker_box",
            "minecraft:cyan_shulker_box",
            "minecraft:purple_shulker_box",
            "minecraft:blue_shulker_box",
            "minecraft:brown_shulker_box",
            "minecraft:green_shulker_box",
            "minecraft:red_shulker_box",
            "minecraft:black_shulker_box"
        ],
        "0": [
            {
                "id": "minecraft:paper",
                "sorter": 8
            },
            {
                "id": "minecraft:book",
                "sorter": 7
            },
            "minecraft:writable_book",
            {
                "id": "minecraft:bookshelf",
                "sorter": 6
            },
            {
                "id": "minecraft:fireworks",
                "sorter": 16,
                "tagValue": 1
            },
            {
                "id": "minecraft:fireworks",
                "sorter": 17,
                "tagValue": 2
            },
            {
                "id": "minecraft:fireworks",
                "sorter": 18,
                "tagValue": 3
            }
        ],
        "1": [
            {
                "id": "minecraft:jukebox",
                "sorter": 9
            },
            {
                "id": "minecraft:record_13",
                "name": "Music Disc: C418 - 13"
            },
            {
                "id": "minecraft:record_cat",
                "name": "Music Disc: C418 - cat"
            },
            {
                "id": "minecraft:record_blocks",
                "name": "Music Disc: C418 - blocks"
            },
            {
                "id": "minecraft:record_chirp",
                "name": "Music Disc: C418 - chirp"
            },
            {
                "id": "minecraft:record_far",
                "name": "Music Disc: C418 - far"
            },
            {
                "id": "minecraft:record_mall",
                "name": "Music Disc: C418 - mall"
            },
            {
                "id": "minecraft:record_mellohi",
                "name": "Music Disc: C418 - mellohi"
            },
            {
                "id": "minecraft:record_stal",
                "name": "Music Disc: C418 - stal"
            },
            {
                "id": "minecraft:record_strad",
                "name": "Music Disc: C418 - strad"
            },
            {
                "id": "minecraft:record_ward",
                "name": "Music Disc: C418 - ward"
            },
            {
                "id": "minecraft:record_11",
                "name": "Music Disc: C418 - 11"
            },
            {
                "id": "minecraft:record_wait",
                "name": "Music Disc: C418 - wait"
            }
        ]
    }
]
